MANIFEST.in
README.rst
setup.cfg
setup.py
docs/Makefile
docs/alternatives.rst
docs/conf.py
docs/contribute.rst
docs/exts.py
docs/index.rst
docs/installation.rst
docs/license.rst
docs/make.bat
docs/quickstart.rst
docs/requirements.txt
docs/api/cli.rst
docs/api/conf.settings.rst
docs/api/index.rst
docs/api/nodes.rst
docs/api/backends/git.rst
docs/api/backends/hg.rst
docs/api/backends/index.rst
docs/api/utils/index.rst
docs/theme/ADC/layout.html
docs/theme/ADC/theme.conf
docs/theme/ADC/static/adctheme.css
docs/theme/ADC/static/breadcrumb_background.png
docs/theme/ADC/static/documentation.png
docs/theme/ADC/static/header_sm_mid.png
docs/theme/ADC/static/mobile.css
docs/theme/ADC/static/scrn1.png
docs/theme/ADC/static/scrn2.png
docs/theme/ADC/static/searchfield_leftcap.png
docs/theme/ADC/static/searchfield_repeat.png
docs/theme/ADC/static/searchfield_rightcap.png
docs/theme/ADC/static/title_background.png
docs/theme/ADC/static/toc.js
docs/theme/ADC/static/triangle_closed.png
docs/theme/ADC/static/triangle_left.png
docs/theme/ADC/static/triangle_open.png
docs/usage/index.rst
docs/usage/vcsrc.rst
managevcs/__init__.py
managevcs/__init__.pyc
managevcs/cli.py
managevcs/cli.pyc
managevcs/exceptions.py
managevcs/exceptions.pyc
managevcs/nodes.py
managevcs/nodes.pyc
managevcs/subprocessio.py
managevcs/subprocessio.pyc
managevcs.egg-info/PKG-INFO
managevcs.egg-info/SOURCES.txt
managevcs.egg-info/dependency_links.txt
managevcs.egg-info/not-zip-safe
managevcs.egg-info/requires.txt
managevcs.egg-info/top_level.txt
managevcs/backends/__init__.py
managevcs/backends/__init__.pyc
managevcs/backends/base.py
managevcs/backends/base.pyc
managevcs/backends/git/__init__.py
managevcs/backends/git/__init__.pyc
managevcs/backends/git/changeset.py
managevcs/backends/git/changeset.pyc
managevcs/backends/git/config.py
managevcs/backends/git/config.pyc
managevcs/backends/git/inmemory.py
managevcs/backends/git/inmemory.pyc
managevcs/backends/git/repository.py
managevcs/backends/git/repository.pyc
managevcs/backends/git/workdir.py
managevcs/backends/git/workdir.pyc
managevcs/backends/hg/__init__.py
managevcs/backends/hg/__init__.pyc
managevcs/backends/hg/changeset.py
