Metadata-Version: 1.1
Name: managevcs
Version: 0.5.2
Summary: UNKNOWN
Home-page: https://github.com/codeinn/managevcs
Author: Marcin Kuzminski, Lukasz Balcerzak, Dmitry Zhiltsov
Author-email: dzhiltsov@me.com
License: UNKNOWN
Platform: UNKNOWN
Classifier: Development Status :: 4 - Beta
Classifier: License :: OSI Approved :: MIT License
Classifier: Intended Audience :: Developers
Classifier: Programming Language :: Python
Classifier: Operating System :: OS Independent
